[
  {
    "id": 1,
    "match_id": 8600397564,
    "tournament_id": null,
    "radiant_team_id": "yakult-brother",
    "dire_team_id": "xtreme-gaming",
    "radiant_score": 18,
    "dire_score": 4,
    "radiant_game_wins": 1,
    "dire_game_wins": 0,
    "start_time": 1765467722,
    "duration": 1501,
    "series_type": "BO3",
    "status": "finished",
    "league_id": 18988,
    "game_mode": null,
    "lobby_type": 7,
    "created_at": 1770479277,
    "updated_at": 1770479277,
    "radiant_team_name": "Yakult Brother",
    "radiant_team_name_cn": "YB",
    "radiant_logo": null,
    "dire_team_name": "Xtreme Gaming",
    "dire_team_name_cn": "XG",
    "dire_logo": null,
    "tournament_name": null,
    "tournament_name_cn": null,
    "tournament_tier": null
  },
  {
    "id": 2,
    "match_id": 8600296592,
    "tournament_id": null,
    "radiant_team_id": "yakult-brother",
    "dire_team_id": "xtreme-gaming",
    "radiant_score": 24,
    "dire_score": 4,
    "radiant_game_wins": 1,
    "dire_game_wins": 0,
    "start_time": 1765464060,
    "duration": 1820,
    "series_type": "BO3",
    "status": "finished",
    "league_id": 18988,
    "game_mode": null,
    "lobby_type": 7,
    "created_at": 1770479277,
    "updated_at": 1770479277,
    "radiant_team_name": "Yakult Brother",
    "radiant_team_name_cn": "YB",
    "radiant_logo": null,
    "dire_team_name": "Xtreme Gaming",
    "dire_team_name_cn": "XG",
    "dire_logo": null,
    "tournament_name": null,
    "tournament_name_cn": null,
    "tournament_tier": null
  },
  {
    "id": 3,
    "match_id": 8514189882,
    "tournament_id": null,
    "radiant_team_id": "yakult-brother",
    "dire_team_id": "yakult-brother",
    "radiant_score": 31,
    "dire_score": 34,
    "radiant_game_wins": 1,
    "dire_game_wins": 0,
    "start_time": 1760635483,
    "duration": 3181,
    "series_type": "BO3",
    "status": "finished",
    "league_id": 17419,
    "game_mode": null,
    "lobby_type": 7,
    "created_at": 1770479277,
    "updated_at": 1770479277,
    "radiant_team_name": "Yakult Brother",
    "radiant_team_name_cn": "YB",
    "radiant_logo": null,
    "dire_team_name": "Yakult Brother",
    "dire_team_name_cn": "YB",
    "dire_logo": null,
    "tournament_name": null,
    "tournament_name_cn": null,
    "tournament_tier": null
  },
  {
    "id": 4,
    "match_id": 8460471023,
    "tournament_id": null,
    "radiant_team_id": "xtreme-gaming",
    "dire_team_id": "yakult-brother",
    "radiant_score": 27,
    "dire_score": 22,
    "radiant_game_wins": 1,
    "dire_game_wins": 0,
    "start_time": 1757796434,
    "duration": 3796,
    "series_type": "BO3",
    "status": "finished",
    "league_id": 18324,
    "game_mode": null,
    "lobby_type": 7,
    "created_at": 1770479277,
    "updated_at": 1770479277,
    "radiant_team_name": "Xtreme Gaming",
    "radiant_team_name_cn": "XG",
    "radiant_logo": null,
    "dire_team_name": "Yakult Brother",
    "dire_team_name_cn": "YB",
    "dire_logo": null,
    "tournament_name": null,
    "tournament_name_cn": null,
    "tournament_tier": null
  },
  {
    "id": 5,
    "match_id": 8460339590,
    "tournament_id": null,
    "radiant_team_id": "xtreme-gaming",
    "dire_team_id": "yakult-brother",
    "radiant_score": 19,
    "dire_score": 14,
    "radiant_game_wins": 1,
    "dire_game_wins": 0,
    "start_time": 1757790768,
    "duration": 3780,
    "series_type": "BO3",
    "status": "finished",
    "league_id": 18324,
    "game_mode": null,
    "lobby_type": 7,
    "created_at": 1770479277,
    "updated_at": 1770479277,
    "radiant_team_name": "Xtreme Gaming",
    "radiant_team_name_cn": "XG",
    "radiant_logo": null,
    "dire_team_name": "Yakult Brother",
    "dire_team_name_cn": "YB",
    "dire_logo": null,
    "tournament_name": null,
    "tournament_name_cn": null,
    "tournament_tier": null
  },
  {
    "id": 6,
    "match_id": 8346321736,
    "tournament_id": null,
    "radiant_team_id": "yakult-brother",
    "dire_team_id": "xtreme-gaming",
    "radiant_score": 34,
    "dire_score": 21,
    "radiant_game_wins": 1,
    "dire_game_wins": 0,
    "start_time": 1750665064,
    "duration": 2583,
    "series_type": "BO3",
    "status": "finished",
    "league_id": 18358,
    "game_mode": null,
    "lobby_type": 7,
    "created_at": 1770479277,
    "updated_at": 1770479277,
    "radiant_team_name": "Yakult Brother",
    "radiant_team_name_cn": "YB",
    "radiant_logo": null,
    "dire_team_name": "Xtreme Gaming",
    "dire_team_name_cn": "XG",
    "dire_logo": null,
    "tournament_name": null,
    "tournament_name_cn": null,
    "tournament_tier": null
  },
  {
    "id": 7,
    "match_id": 8346288771,
    "tournament_id": null,
    "radiant_team_id": "xtreme-gaming",
    "dire_team_id": "yakult-brother",
    "radiant_score": 4,
    "dire_score": 22,
    "radiant_game_wins": 0,
    "dire_game_wins": 1,
    "start_time": 1750662012,
    "duration": 1535,
    "series_type": "BO3",
    "status": "finished",
    "league_id": 18358,
    "game_mode": null,
    "lobby_type": 7,
    "created_at": 1770479277,
    "updated_at": 1770479277,
    "radiant_team_name": "Xtreme Gaming",
    "radiant_team_name_cn": "XG",
    "radiant_logo": null,
    "dire_team_name": "Yakult Brother",
    "dire_team_name_cn": "YB",
    "dire_logo": null,
    "tournament_name": null,
    "tournament_name_cn": null,
    "tournament_tier": null
  },
  {
    "id": 8,
    "match_id": 8312730139,
    "tournament_id": null,
    "radiant_team_id": "yakult-brother",
    "dire_team_id": "yakult-brother",
    "radiant_score": 28,
    "dire_score": 30,
    "radiant_game_wins": 0,
    "dire_game_wins": 1,
    "start_time": 1748525220,
    "duration": 2696,
    "series_type": "BO3",
    "status": "finished",
    "league_id": 18111,
    "game_mode": null,
    "lobby_type": 7,
    "created_at": 1770479277,
    "updated_at": 1770479277,
    "radiant_team_name": "Yakult Brother",
    "radiant_team_name_cn": "YB",
    "radiant_logo": null,
    "dire_team_name": "Yakult Brother",
    "dire_team_name_cn": "YB",
    "dire_logo": null,
    "tournament_name": null,
    "tournament_name_cn": null,
    "tournament_tier": null
  },
  {
    "id": 9,
    "match_id": 8312622965,
    "tournament_id": null,
    "radiant_team_id": "yakult-brother",
    "dire_team_id": "yakult-brother",
    "radiant_score": 28,
    "dire_score": 17,
    "radiant_game_wins": 1,
    "dire_game_wins": 0,
    "start_time": 1748521500,
    "duration": 2128,
    "series_type": "BO3",
    "status": "finished",
    "league_id": 18111,
    "game_mode": null,
    "lobby_type": 7,
    "created_at": 1770479277,
    "updated_at": 1770479277,
    "radiant_team_name": "Yakult Brother",
    "radiant_team_name_cn": "YB",
    "radiant_logo": null,
    "dire_team_name": "Yakult Brother",
    "dire_team_name_cn": "YB",
    "dire_logo": null,
    "tournament_name": null,
    "tournament_name_cn": null,
    "tournament_tier": null
  },
  {
    "id": 10,
    "match_id": 8300887097,
    "tournament_id": null,
    "radiant_team_id": "xtreme-gaming",
    "dire_team_id": "yakult-brother",
    "radiant_score": 29,
    "dire_score": 20,
    "radiant_game_wins": 1,
    "dire_game_wins": 0,
    "start_time": 1747757700,
    "duration": 2592,
    "series_type": "BO3",
    "status": "finished",
    "league_id": 18111,
    "game_mode": null,
    "lobby_type": 7,
    "created_at": 1770479277,
    "updated_at": 1770479277,
    "radiant_team_name": "Xtreme Gaming",
    "radiant_team_name_cn": "XG",
    "radiant_logo": null,
    "dire_team_name": "Yakult Brother",
    "dire_team_name_cn": "YB",
    "dire_logo": null,
    "tournament_name": null,
    "tournament_name_cn": null,
    "tournament_tier": null
  },
  {
    "id": 11,
    "match_id": 8300785884,
    "tournament_id": null,
    "radiant_team_id": "yakult-brother",
    "dire_team_id": "xtreme-gaming",
    "radiant_score": 33,
    "dire_score": 22,
    "radiant_game_wins": 1,
    "dire_game_wins": 0,
    "start_time": 1747752900,
    "duration": 3080,
    "series_type": "BO3",
    "status": "finished",
    "league_id": 18111,
    "game_mode": null,
    "lobby_type": 7,
    "created_at": 1770479277,
    "updated_at": 1770479277,
    "radiant_team_name": "Yakult Brother",
    "radiant_team_name_cn": "YB",
    "radiant_logo": null,
    "dire_team_name": "Xtreme Gaming",
    "dire_team_name_cn": "XG",
    "dire_logo": null,
    "tournament_name": null,
    "tournament_name_cn": null,
    "tournament_tier": null
  },
  {
    "id": 12,
    "match_id": 8282518155,
    "tournament_id": null,
    "radiant_team_id": "xtreme-gaming",
    "dire_team_id": "yakult-brother",
    "radiant_score": 24,
    "dire_score": 7,
    "radiant_game_wins": 1,
    "dire_game_wins": 0,
    "start_time": 1746526702,
    "duration": 1764,
    "series_type": "BO3",
    "status": "finished",
    "league_id": 17418,
    "game_mode": null,
    "lobby_type": 7,
    "created_at": 1770479277,
    "updated_at": 1770479277,
    "radiant_team_name": "Xtreme Gaming",
    "radiant_team_name_cn": "XG",
    "radiant_logo": null,
    "dire_team_name": "Yakult Brother",
    "dire_team_name_cn": "YB",
    "dire_logo": null,
    "tournament_name": null,
    "tournament_name_cn": null,
    "tournament_tier": null
  },
  {
    "id": 13,
    "match_id": 8176424546,
    "tournament_id": null,
    "radiant_team_id": "xtreme-gaming",
    "dire_team_id": "yakult-brother",
    "radiant_score": 9,
    "dire_score": 28,
    "radiant_game_wins": 0,
    "dire_game_wins": 1,
    "start_time": 1739707802,
    "duration": 1563,
    "series_type": "BO3",
    "status": "finished",
    "league_id": 17765,
    "game_mode": null,
    "lobby_type": 7,
    "created_at": 1770479278,
    "updated_at": 1770479278,
    "radiant_team_name": "Xtreme Gaming",
    "radiant_team_name_cn": "XG",
    "radiant_logo": null,
    "dire_team_name": "Yakult Brother",
    "dire_team_name_cn": "YB",
    "dire_logo": null,
    "tournament_name": null,
    "tournament_name_cn": null,
    "tournament_tier": null
  },
  {
    "id": 14,
    "match_id": 8176324556,
    "tournament_id": null,
    "radiant_team_id": "yakult-brother",
    "dire_team_id": "xtreme-gaming",
    "radiant_score": 39,
    "dire_score": 28,
    "radiant_game_wins": 1,
    "dire_game_wins": 0,
    "start_time": 1739703302,
    "duration": 2344,
    "series_type": "BO3",
    "status": "finished",
    "league_id": 17765,
    "game_mode": null,
    "lobby_type": 7,
    "created_at": 1770479278,
    "updated_at": 1770479278,
    "radiant_team_name": "Yakult Brother",
    "radiant_team_name_cn": "YB",
    "radiant_logo": null,
    "dire_team_name": "Xtreme Gaming",
    "dire_team_name_cn": "XG",
    "dire_logo": null,
    "tournament_name": null,
    "tournament_name_cn": null,
    "tournament_tier": null
  },
  {
    "id": 15,
    "match_id": 8161073030,
    "tournament_id": null,
    "radiant_team_id": "xtreme-gaming",
    "dire_team_id": "yakult-brother",
    "radiant_score": 7,
    "dire_score": 29,
    "radiant_game_wins": 0,
    "dire_game_wins": 1,
    "start_time": 1738781482,
    "duration": 1744,
    "series_type": "BO3",
    "status": "finished",
    "league_id": 17417,
    "game_mode": null,
    "lobby_type": 7,
    "created_at": 1770479278,
    "updated_at": 1770479278,
    "radiant_team_name": "Xtreme Gaming",
    "radiant_team_name_cn": "XG",
    "radiant_logo": null,
    "dire_team_name": "Yakult Brother",
    "dire_team_name_cn": "YB",
    "dire_logo": null,
    "tournament_name": null,
    "tournament_name_cn": null,
    "tournament_tier": null
  },
  {
    "id": 16,
    "match_id": 8160957815,
    "tournament_id": null,
    "radiant_team_id": "yakult-brother",
    "dire_team_id": "xtreme-gaming",
    "radiant_score": 29,
    "dire_score": 16,
    "radiant_game_wins": 1,
    "dire_game_wins": 0,
    "start_time": 1738776592,
    "duration": 2463,
    "series_type": "BO3",
    "status": "finished",
    "league_id": 17417,
    "game_mode": null,
    "lobby_type": 7,
    "created_at": 1770479278,
    "updated_at": 1770479278,
    "radiant_team_name": "Yakult Brother",
    "radiant_team_name_cn": "YB",
    "radiant_logo": null,
    "dire_team_name": "Xtreme Gaming",
    "dire_team_name_cn": "XG",
    "dire_logo": null,
    "tournament_name": null,
    "tournament_name_cn": null,
    "tournament_tier": null
  },
  {
    "id": 17,
    "match_id": 8158998679,
    "tournament_id": null,
    "radiant_team_id": "yakult-brother",
    "dire_team_id": "yakult-brother",
    "radiant_score": 42,
    "dire_score": 5,
    "radiant_game_wins": 1,
    "dire_game_wins": 0,
    "start_time": 1738662567,
    "duration": 1607,
    "series_type": "BO3",
    "status": "finished",
    "league_id": 17417,
    "game_mode": null,
    "lobby_type": 7,
    "created_at": 1770479278,
    "updated_at": 1770479278,
    "radiant_team_name": "Yakult Brother",
    "radiant_team_name_cn": "YB",
    "radiant_logo": null,
    "dire_team_name": "Yakult Brother",
    "dire_team_name_cn": "YB",
    "dire_logo": null,
    "tournament_name": null,
    "tournament_name_cn": null,
    "tournament_tier": null
  },
  {
    "id": 18,
    "match_id": 8054846912,
    "tournament_id": null,
    "radiant_team_id": "xtreme-gaming",
    "dire_team_id": "yakult-brother",
    "radiant_score": 9,
    "dire_score": 24,
    "radiant_game_wins": 0,
    "dire_game_wins": 1,
    "start_time": 1732625998,
    "duration": 1743,
    "series_type": "BO3",
    "status": "finished",
    "league_id": 17414,
    "game_mode": null,
    "lobby_type": 7,
    "created_at": 1770479278,
    "updated_at": 1770479278,
    "radiant_team_name": "Xtreme Gaming",
    "radiant_team_name_cn": "XG",
    "radiant_logo": null,
    "dire_team_name": "Yakult Brother",
    "dire_team_name_cn": "YB",
    "dire_logo": null,
    "tournament_name": null,
    "tournament_name_cn": null,
    "tournament_tier": null
  },
  {
    "id": 19,
    "match_id": 8015615203,
    "tournament_id": null,
    "radiant_team_id": "yakult-brother",
    "dire_team_id": "xtreme-gaming",
    "radiant_score": 29,
    "dire_score": 8,
    "radiant_game_wins": 1,
    "dire_game_wins": 0,
    "start_time": 1730549700,
    "duration": 1809,
    "series_type": "BO3",
    "status": "finished",
    "league_id": 17272,
    "game_mode": null,
    "lobby_type": 7,
    "created_at": 1770479278,
    "updated_at": 1770479278,
    "radiant_team_name": "Yakult Brother",
    "radiant_team_name_cn": "YB",
    "radiant_logo": null,
    "dire_team_name": "Xtreme Gaming",
    "dire_team_name_cn": "XG",
    "dire_logo": null,
    "tournament_name": null,
    "tournament_name_cn": null,
    "tournament_tier": null
  },
  {
    "id": 20,
    "match_id": 8015519857,
    "tournament_id": null,
    "radiant_team_id": "xtreme-gaming",
    "dire_team_id": "yakult-brother",
    "radiant_score": 32,
    "dire_score": 12,
    "radiant_game_wins": 1,
    "dire_game_wins": 0,
    "start_time": 1730545740,
    "duration": 2203,
    "series_type": "BO3",
    "status": "finished",
    "league_id": 17272,
    "game_mode": null,
    "lobby_type": 7,
    "created_at": 1770479278,
    "updated_at": 1770479278,
    "radiant_team_name": "Xtreme Gaming",
    "radiant_team_name_cn": "XG",
    "radiant_logo": null,
    "dire_team_name": "Yakult Brother",
    "dire_team_name_cn": "YB",
    "dire_logo": null,
    "tournament_name": null,
    "tournament_name_cn": null,
    "tournament_tier": null
  },
  {
    "id": 21,
    "match_id": 8015433695,
    "tournament_id": null,
    "radiant_team_id": "yakult-brother",
    "dire_team_id": "xtreme-gaming",
    "radiant_score": 26,
    "dire_score": 14,
    "radiant_game_wins": 1,
    "dire_game_wins": 0,
    "start_time": 1730541301,
    "duration": 2550,
    "series_type": "BO3",
    "status": "finished",
    "league_id": 17272,
    "game_mode": null,
    "lobby_type": 7,
    "created_at": 1770479278,
    "updated_at": 1770479278,
    "radiant_team_name": "Yakult Brother",
    "radiant_team_name_cn": "YB",
    "radiant_logo": null,
    "dire_team_name": "Xtreme Gaming",
    "dire_team_name_cn": "XG",
    "dire_logo": null,
    "tournament_name": null,
    "tournament_name_cn": null,
    "tournament_tier": null
  },
  {
    "id": 22,
    "match_id": 8008222782,
    "tournament_id": null,
    "radiant_team_id": "yakult-brother",
    "dire_team_id": "xtreme-gaming",
    "radiant_score": 21,
    "dire_score": 30,
    "radiant_game_wins": 0,
    "dire_game_wins": 1,
    "start_time": 1730116920,
    "duration": 2446,
    "series_type": "BO3",
    "status": "finished",
    "league_id": 17272,
    "game_mode": null,
    "lobby_type": 7,
    "created_at": 1770479278,
    "updated_at": 1770479278,
    "radiant_team_name": "Yakult Brother",
    "radiant_team_name_cn": "YB",
    "radiant_logo": null,
    "dire_team_name": "Xtreme Gaming",
    "dire_team_name_cn": "XG",
    "dire_logo": null,
    "tournament_name": null,
    "tournament_name_cn": null,
    "tournament_tier": null
  },
  {
    "id": 23,
    "match_id": 8008149335,
    "tournament_id": null,
    "radiant_team_id": "xtreme-gaming",
    "dire_team_id": "yakult-brother",
    "radiant_score": 29,
    "dire_score": 16,
    "radiant_game_wins": 1,
    "dire_game_wins": 0,
    "start_time": 1730112900,
    "duration": 2296,
    "series_type": "BO3",
    "status": "finished",
    "league_id": 17272,
    "game_mode": null,
    "lobby_type": 7,
    "created_at": 1770479278,
    "updated_at": 1770479278,
    "radiant_team_name": "Xtreme Gaming",
    "radiant_team_name_cn": "XG",
    "radiant_logo": null,
    "dire_team_name": "Yakult Brother",
    "dire_team_name_cn": "YB",
    "dire_logo": null,
    "tournament_name": null,
    "tournament_name_cn": null,
    "tournament_tier": null
  },
  {
    "id": 24,
    "match_id": 8003277731,
    "tournament_id": null,
    "radiant_team_id": "yakult-brother",
    "dire_team_id": "yakult-brother",
    "radiant_score": 27,
    "dire_score": 27,
    "radiant_game_wins": 1,
    "dire_game_wins": 0,
    "start_time": 1729858741,
    "duration": 3231,
    "series_type": "BO3",
    "status": "finished",
    "league_id": 17126,
    "game_mode": null,
    "lobby_type": 7,
    "created_at": 1770479278,
    "updated_at": 1770479278,
    "radiant_team_name": "Yakult Brother",
    "radiant_team_name_cn": "YB",
    "radiant_logo": null,
    "dire_team_name": "Yakult Brother",
    "dire_team_name_cn": "YB",
    "dire_logo": null,
    "tournament_name": null,
    "tournament_name_cn": null,
    "tournament_tier": null
  },
  {
    "id": 25,
    "match_id": 8003188735,
    "tournament_id": null,
    "radiant_team_id": "yakult-brother",
    "dire_team_id": "yakult-brother",
    "radiant_score": 17,
    "dire_score": 37,
    "radiant_game_wins": 0,
    "dire_game_wins": 1,
    "start_time": 1729854300,
    "duration": 2631,
    "series_type": "BO3",
    "status": "finished",
    "league_id": 17126,
    "game_mode": null,
    "lobby_type": 7,
    "created_at": 1770479278,
    "updated_at": 1770479278,
    "radiant_team_name": "Yakult Brother",
    "radiant_team_name_cn": "YB",
    "radiant_logo": null,
    "dire_team_name": "Yakult Brother",
    "dire_team_name_cn": "YB",
    "dire_logo": null,
    "tournament_name": null,
    "tournament_name_cn": null,
    "tournament_tier": null
  },
  {
    "id": 26,
    "match_id": 7997964737,
    "tournament_id": null,
    "radiant_team_id": "yakult-brother",
    "dire_team_id": "yakult-brother",
    "radiant_score": 32,
    "dire_score": 16,
    "radiant_game_wins": 1,
    "dire_game_wins": 0,
    "start_time": 1729522300,
    "duration": 2158,
    "series_type": "BO3",
    "status": "finished",
    "league_id": 17126,
    "game_mode": null,
    "lobby_type": 7,
    "created_at": 1770479278,
    "updated_at": 1770479278,
    "radiant_team_name": "Yakult Brother",
    "radiant_team_name_cn": "YB",
    "radiant_logo": null,
    "dire_team_name": "Yakult Brother",
    "dire_team_name_cn": "YB",
    "dire_logo": null,
    "tournament_name": null,
    "tournament_name_cn": null,
    "tournament_tier": null
  },
  {
    "id": 27,
    "match_id": 7997845167,
    "tournament_id": null,
    "radiant_team_id": "yakult-brother",
    "dire_team_id": "yakult-brother",
    "radiant_score": 35,
    "dire_score": 19,
    "radiant_game_wins": 1,
    "dire_game_wins": 0,
    "start_time": 1729517821,
    "duration": 2802,
    "series_type": "BO3",
    "status": "finished",
    "league_id": 17126,
    "game_mode": null,
    "lobby_type": 7,
    "created_at": 1770479278,
    "updated_at": 1770479278,
    "radiant_team_name": "Yakult Brother",
    "radiant_team_name_cn": "YB",
    "radiant_logo": null,
    "dire_team_name": "Yakult Brother",
    "dire_team_name_cn": "YB",
    "dire_logo": null,
    "tournament_name": null,
    "tournament_name_cn": null,
    "tournament_tier": null
  },
  {
    "id": 28,
    "match_id": 7756985078,
    "tournament_id": null,
    "radiant_team_id": "xtreme-gaming",
    "dire_team_id": "yakult-brother",
    "radiant_score": 5,
    "dire_score": 22,
    "radiant_game_wins": 0,
    "dire_game_wins": 1,
    "start_time": 1716661500,
    "duration": 1775,
    "series_type": "BO3",
    "status": "finished",
    "league_id": 16632,
    "game_mode": null,
    "lobby_type": 7,
    "created_at": 1770479278,
    "updated_at": 1770479278,
    "radiant_team_name": "Xtreme Gaming",
    "radiant_team_name_cn": "XG",
    "radiant_logo": null,
    "dire_team_name": "Yakult Brother",
    "dire_team_name_cn": "YB",
    "dire_logo": null,
    "tournament_name": null,
    "tournament_name_cn": null,
    "tournament_tier": null
  },
  {
    "id": 29,
    "match_id": 7756811275,
    "tournament_id": null,
    "radiant_team_id": "yakult-brother",
    "dire_team_id": "xtreme-gaming",
    "radiant_score": 40,
    "dire_score": 11,
    "radiant_game_wins": 1,
    "dire_game_wins": 0,
    "start_time": 1716656400,
    "duration": 3235,
    "series_type": "BO3",
    "status": "finished",
    "league_id": 16632,
    "game_mode": null,
    "lobby_type": 7,
    "created_at": 1770479278,
    "updated_at": 1770479278,
    "radiant_team_name": "Yakult Brother",
    "radiant_team_name_cn": "YB",
    "radiant_logo": null,
    "dire_team_name": "Xtreme Gaming",
    "dire_team_name_cn": "XG",
    "dire_logo": null,
    "tournament_name": null,
    "tournament_name_cn": null,
    "tournament_tier": null
  },
  {
    "id": 30,
    "match_id": 7747400927,
    "tournament_id": null,
    "radiant_team_id": "yakult-brother",
    "dire_team_id": "yakult-brother",
    "radiant_score": 28,
    "dire_score": 14,
    "radiant_game_wins": 1,
    "dire_game_wins": 0,
    "start_time": 1716233819,
    "duration": 2809,
    "series_type": "BO3",
    "status": "finished",
    "league_id": 16632,
    "game_mode": null,
    "lobby_type": 7,
    "created_at": 1770479278,
    "updated_at": 1770479278,
    "radiant_team_name": "Yakult Brother",
    "radiant_team_name_cn": "YB",
    "radiant_logo": null,
    "dire_team_name": "Yakult Brother",
    "dire_team_name_cn": "YB",
    "dire_logo": null,
    "tournament_name": null,
    "tournament_name_cn": null,
    "tournament_tier": null
  },
  {
    "id": 31,
    "match_id": 7747296234,
    "tournament_id": null,
    "radiant_team_id": "yakult-brother",
    "dire_team_id": "yakult-brother",
    "radiant_score": 19,
    "dire_score": 28,
    "radiant_game_wins": 0,
    "dire_game_wins": 1,
    "start_time": 1716229260,
    "duration": 2725,
    "series_type": "BO3",
    "status": "finished",
    "league_id": 16632,
    "game_mode": null,
    "lobby_type": 7,
    "created_at": 1770479278,
    "updated_at": 1770479278,
    "radiant_team_name": "Yakult Brother",
    "radiant_team_name_cn": "YB",
    "radiant_logo": null,
    "dire_team_name": "Yakult Brother",
    "dire_team_name_cn": "YB",
    "dire_logo": null,
    "tournament_name": null,
    "tournament_name_cn": null,
    "tournament_tier": null
  },
  {
    "id": 32,
    "match_id": 7673622272,
    "tournament_id": null,
    "radiant_team_id": "xtreme-gaming",
    "dire_team_id": "yakult-brother",
    "radiant_score": 13,
    "dire_score": 39,
    "radiant_game_wins": 0,
    "dire_game_wins": 1,
    "start_time": 1712432131,
    "duration": 2767,
    "series_type": "BO3",
    "status": "finished",
    "league_id": 16483,
    "game_mode": null,
    "lobby_type": 7,
    "created_at": 1770479278,
    "updated_at": 1770479278,
    "radiant_team_name": "Xtreme Gaming",
    "radiant_team_name_cn": "XG",
    "radiant_logo": null,
    "dire_team_name": "Yakult Brother",
    "dire_team_name_cn": "YB",
    "dire_logo": null,
    "tournament_name": null,
    "tournament_name_cn": null,
    "tournament_tier": null
  },
  {
    "id": 33,
    "match_id": 7673512852,
    "tournament_id": null,
    "radiant_team_id": "yakult-brother",
    "dire_team_id": "xtreme-gaming",
    "radiant_score": 33,
    "dire_score": 24,
    "radiant_game_wins": 0,
    "dire_game_wins": 1,
    "start_time": 1712427449,
    "duration": 2845,
    "series_type": "BO3",
    "status": "finished",
    "league_id": 16483,
    "game_mode": null,
    "lobby_type": 7,
    "created_at": 1770479278,
    "updated_at": 1770479278,
    "radiant_team_name": "Yakult Brother",
    "radiant_team_name_cn": "YB",
    "radiant_logo": null,
    "dire_team_name": "Xtreme Gaming",
    "dire_team_name_cn": "XG",
    "dire_logo": null,
    "tournament_name": null,
    "tournament_name_cn": null,
    "tournament_tier": null
  },
  {
    "id": 34,
    "match_id": 7630422621,
    "tournament_id": null,
    "radiant_team_id": "xtreme-gaming",
    "dire_team_id": "yakult-brother",
    "radiant_score": 13,
    "dire_score": 20,
    "radiant_game_wins": 0,
    "dire_game_wins": 1,
    "start_time": 1710076198,
    "duration": 2272,
    "series_type": "BO3",
    "status": "finished",
    "league_id": 16201,
    "game_mode": null,
    "lobby_type": 7,
    "created_at": 1770479278,
    "updated_at": 1770479278,
    "radiant_team_name": "Xtreme Gaming",
    "radiant_team_name_cn": "XG",
    "radiant_logo": null,
    "dire_team_name": "Yakult Brother",
    "dire_team_name_cn": "YB",
    "dire_logo": null,
    "tournament_name": null,
    "tournament_name_cn": null,
    "tournament_tier": null
  },
  {
    "id": 35,
    "match_id": 7630302858,
    "tournament_id": null,
    "radiant_team_id": "yakult-brother",
    "dire_team_id": "xtreme-gaming",
    "radiant_score": 26,
    "dire_score": 14,
    "radiant_game_wins": 1,
    "dire_game_wins": 0,
    "start_time": 1710071769,
    "duration": 2646,
    "series_type": "BO3",
    "status": "finished",
    "league_id": 16201,
    "game_mode": null,
    "lobby_type": 7,
    "created_at": 1770479278,
    "updated_at": 1770479278,
    "radiant_team_name": "Yakult Brother",
    "radiant_team_name_cn": "YB",
    "radiant_logo": null,
    "dire_team_name": "Xtreme Gaming",
    "dire_team_name_cn": "XG",
    "dire_logo": null,
    "tournament_name": null,
    "tournament_name_cn": null,
    "tournament_tier": null
  },
  {
    "id": 36,
    "match_id": 7616882903,
    "tournament_id": null,
    "radiant_team_id": "xtreme-gaming",
    "dire_team_id": "yakult-brother",
    "radiant_score": 10,
    "dire_score": 22,
    "radiant_game_wins": 0,
    "dire_game_wins": 1,
    "start_time": 1709381156,
    "duration": 2100,
    "series_type": "BO3",
    "status": "finished",
    "league_id": 16201,
    "game_mode": null,
    "lobby_type": 7,
    "created_at": 1770479278,
    "updated_at": 1770479278,
    "radiant_team_name": "Xtreme Gaming",
    "radiant_team_name_cn": "XG",
    "radiant_logo": null,
    "dire_team_name": "Yakult Brother",
    "dire_team_name_cn": "YB",
    "dire_logo": null,
    "tournament_name": null,
    "tournament_name_cn": null,
    "tournament_tier": null
  },
  {
    "id": 37,
    "match_id": 7616783111,
    "tournament_id": null,
    "radiant_team_id": "yakult-brother",
    "dire_team_id": "xtreme-gaming",
    "radiant_score": 4,
    "dire_score": 12,
    "radiant_game_wins": 0,
    "dire_game_wins": 1,
    "start_time": 1709377676,
    "duration": 1634,
    "series_type": "BO3",
    "status": "finished",
    "league_id": 16201,
    "game_mode": null,
    "lobby_type": 7,
    "created_at": 1770479278,
    "updated_at": 1770479278,
    "radiant_team_name": "Yakult Brother",
    "radiant_team_name_cn": "YB",
    "radiant_logo": null,
    "dire_team_name": "Xtreme Gaming",
    "dire_team_name_cn": "XG",
    "dire_logo": null,
    "tournament_name": null,
    "tournament_name_cn": null,
    "tournament_tier": null
  },
  {
    "id": 38,
    "match_id": 7616693091,
    "tournament_id": null,
    "radiant_team_id": "xtreme-gaming",
    "dire_team_id": "yakult-brother",
    "radiant_score": 15,
    "dire_score": 26,
    "radiant_game_wins": 0,
    "dire_game_wins": 1,
    "start_time": 1709373296,
    "duration": 2392,
    "series_type": "BO3",
    "status": "finished",
    "league_id": 16201,
    "game_mode": null,
    "lobby_type": 7,
    "created_at": 1770479278,
    "updated_at": 1770479278,
    "radiant_team_name": "Xtreme Gaming",
    "radiant_team_name_cn": "XG",
    "radiant_logo": null,
    "dire_team_name": "Yakult Brother",
    "dire_team_name_cn": "YB",
    "dire_logo": null,
    "tournament_name": null,
    "tournament_name_cn": null,
    "tournament_tier": null
  },
  {
    "id": 39,
    "match_id": 7608867500,
    "tournament_id": null,
    "radiant_team_id": "yakult-brother",
    "dire_team_id": "yakult-brother",
    "radiant_score": 24,
    "dire_score": 11,
    "radiant_game_wins": 1,
    "dire_game_wins": 0,
    "start_time": 1708950915,
    "duration": 1675,
    "series_type": "BO3",
    "status": "finished",
    "league_id": 16201,
    "game_mode": null,
    "lobby_type": 7,
    "created_at": 1770479278,
    "updated_at": 1770479278,
    "radiant_team_name": "Yakult Brother",
    "radiant_team_name_cn": "YB",
    "radiant_logo": null,
    "dire_team_name": "Yakult Brother",
    "dire_team_name_cn": "YB",
    "dire_logo": null,
    "tournament_name": null,
    "tournament_name_cn": null,
    "tournament_tier": null
  },
  {
    "id": 40,
    "match_id": 7608734818,
    "tournament_id": null,
    "radiant_team_id": "yakult-brother",
    "dire_team_id": "yakult-brother",
    "radiant_score": 32,
    "dire_score": 20,
    "radiant_game_wins": 1,
    "dire_game_wins": 0,
    "start_time": 1708945395,
    "duration": 3562,
    "series_type": "BO3",
    "status": "finished",
    "league_id": 16201,
    "game_mode": null,
    "lobby_type": 7,
    "created_at": 1770479278,
    "updated_at": 1770479278,
    "radiant_team_name": "Yakult Brother",
    "radiant_team_name_cn": "YB",
    "radiant_logo": null,
    "dire_team_name": "Yakult Brother",
    "dire_team_name_cn": "YB",
    "dire_logo": null,
    "tournament_name": null,
    "tournament_name_cn": null,
    "tournament_tier": null
  },
  {
    "id": 41,
    "match_id": 7575775435,
    "tournament_id": null,
    "radiant_team_id": "yakult-brother",
    "dire_team_id": "yakult-brother",
    "radiant_score": 26,
    "dire_score": 31,
    "radiant_game_wins": 1,
    "dire_game_wins": 0,
    "start_time": 1707398102,
    "duration": 2427,
    "series_type": "BO3",
    "status": "finished",
    "league_id": 16169,
    "game_mode": null,
    "lobby_type": 7,
    "created_at": 1770479278,
    "updated_at": 1770479278,
    "radiant_team_name": "Yakult Brother",
    "radiant_team_name_cn": "YB",
    "radiant_logo": null,
    "dire_team_name": "Yakult Brother",
    "dire_team_name_cn": "YB",
    "dire_logo": null,
    "tournament_name": null,
    "tournament_name_cn": null,
    "tournament_tier": null
  },
  {
    "id": 42,
    "match_id": 7575671228,
    "tournament_id": null,
    "radiant_team_id": "yakult-brother",
    "dire_team_id": "yakult-brother",
    "radiant_score": 18,
    "dire_score": 27,
    "radiant_game_wins": 0,
    "dire_game_wins": 1,
    "start_time": 1707393963,
    "duration": 2302,
    "series_type": "BO3",
    "status": "finished",
    "league_id": 16169,
    "game_mode": null,
    "lobby_type": 7,
    "created_at": 1770479278,
    "updated_at": 1770479278,
    "radiant_team_name": "Yakult Brother",
    "radiant_team_name_cn": "YB",
    "radiant_logo": null,
    "dire_team_name": "Yakult Brother",
    "dire_team_name_cn": "YB",
    "dire_logo": null,
    "tournament_name": null,
    "tournament_name_cn": null,
    "tournament_tier": null
  },
  {
    "id": 43,
    "match_id": 7568895441,
    "tournament_id": null,
    "radiant_team_id": "yakult-brother",
    "dire_team_id": "xtreme-gaming",
    "radiant_score": 11,
    "dire_score": 26,
    "radiant_game_wins": 0,
    "dire_game_wins": 1,
    "start_time": 1707043402,
    "duration": 2264,
    "series_type": "BO3",
    "status": "finished",
    "league_id": 16169,
    "game_mode": null,
    "lobby_type": 7,
    "created_at": 1770479278,
    "updated_at": 1770479278,
    "radiant_team_name": "Yakult Brother",
    "radiant_team_name_cn": "YB",
    "radiant_logo": null,
    "dire_team_name": "Xtreme Gaming",
    "dire_team_name_cn": "XG",
    "dire_logo": null,
    "tournament_name": null,
    "tournament_name_cn": null,
    "tournament_tier": null
  },
  {
    "id": 44,
    "match_id": 7568781105,
    "tournament_id": null,
    "radiant_team_id": "yakult-brother",
    "dire_team_id": "xtreme-gaming",
    "radiant_score": 20,
    "dire_score": 25,
    "radiant_game_wins": 0,
    "dire_game_wins": 1,
    "start_time": 1707038851,
    "duration": 2538,
    "series_type": "BO3",
    "status": "finished",
    "league_id": 16169,
    "game_mode": null,
    "lobby_type": 7,
    "created_at": 1770479278,
    "updated_at": 1770479278,
    "radiant_team_name": "Yakult Brother",
    "radiant_team_name_cn": "YB",
    "radiant_logo": null,
    "dire_team_name": "Xtreme Gaming",
    "dire_team_name_cn": "XG",
    "dire_logo": null,
    "tournament_name": null,
    "tournament_name_cn": null,
    "tournament_tier": null
  },
  {
    "id": 45,
    "match_id": 7484406783,
    "tournament_id": null,
    "radiant_team_id": "yakult-brother",
    "dire_team_id": "yakult-brother",
    "radiant_score": 10,
    "dire_score": 27,
    "radiant_game_wins": 0,
    "dire_game_wins": 1,
    "start_time": 1702368002,
    "duration": 2204,
    "series_type": "BO3",
    "status": "finished",
    "league_id": 15910,
    "game_mode": null,
    "lobby_type": 7,
    "created_at": 1770479278,
    "updated_at": 1770479278,
    "radiant_team_name": "Yakult Brother",
    "radiant_team_name_cn": "YB",
    "radiant_logo": null,
    "dire_team_name": "Yakult Brother",
    "dire_team_name_cn": "YB",
    "dire_logo": null,
    "tournament_name": null,
    "tournament_name_cn": null,
    "tournament_tier": null
  },
  {
    "id": 46,
    "match_id": 7484365711,
    "tournament_id": null,
    "radiant_team_id": "yakult-brother",
    "dire_team_id": "yakult-brother",
    "radiant_score": 9,
    "dire_score": 26,
    "radiant_game_wins": 0,
    "dire_game_wins": 1,
    "start_time": 1702364403,
    "duration": 1802,
    "series_type": "BO3",
    "status": "finished",
    "league_id": 15910,
    "game_mode": null,
    "lobby_type": 7,
    "created_at": 1770479278,
    "updated_at": 1770479278,
    "radiant_team_name": "Yakult Brother",
    "radiant_team_name_cn": "YB",
    "radiant_logo": null,
    "dire_team_name": "Yakult Brother",
    "dire_team_name_cn": "YB",
    "dire_logo": null,
    "tournament_name": null,
    "tournament_name_cn": null,
    "tournament_tier": null
  },
  {
    "id": 47,
    "match_id": 7404713057,
    "tournament_id": null,
    "radiant_team_id": "yakult-brother",
    "dire_team_id": "yakult-brother",
    "radiant_score": 17,
    "dire_score": 20,
    "radiant_game_wins": 0,
    "dire_game_wins": 1,
    "start_time": 1698535873,
    "duration": 2569,
    "series_type": "BO3",
    "status": "finished",
    "league_id": 15728,
    "game_mode": null,
    "lobby_type": 7,
    "created_at": 1770479278,
    "updated_at": 1770479278,
    "radiant_team_name": "Yakult Brother",
    "radiant_team_name_cn": "YB",
    "radiant_logo": null,
    "dire_team_name": "Yakult Brother",
    "dire_team_name_cn": "YB",
    "dire_logo": null,
    "tournament_name": null,
    "tournament_name_cn": null,
    "tournament_tier": null
  },
  {
    "id": 48,
    "match_id": 7404668056,
    "tournament_id": null,
    "radiant_team_id": "yakult-brother",
    "dire_team_id": "yakult-brother",
    "radiant_score": 35,
    "dire_score": 5,
    "radiant_game_wins": 1,
    "dire_game_wins": 0,
    "start_time": 1698532296,
    "duration": 1921,
    "series_type": "BO3",
    "status": "finished",
    "league_id": 15728,
    "game_mode": null,
    "lobby_type": 7,
    "created_at": 1770479278,
    "updated_at": 1770479278,
    "radiant_team_name": "Yakult Brother",
    "radiant_team_name_cn": "YB",
    "radiant_logo": null,
    "dire_team_name": "Yakult Brother",
    "dire_team_name_cn": "YB",
    "dire_logo": null,
    "tournament_name": null,
    "tournament_name_cn": null,
    "tournament_tier": null
  },
  {
    "id": 49,
    "match_id": 7404577536,
    "tournament_id": null,
    "radiant_team_id": "yakult-brother",
    "dire_team_id": "yakult-brother",
    "radiant_score": 31,
    "dire_score": 35,
    "radiant_game_wins": 1,
    "dire_game_wins": 0,
    "start_time": 1698526803,
    "duration": 3521,
    "series_type": "BO3",
    "status": "finished",
    "league_id": 15728,
    "game_mode": null,
    "lobby_type": 7,
    "created_at": 1770479278,
    "updated_at": 1770479278,
    "radiant_team_name": "Yakult Brother",
    "radiant_team_name_cn": "YB",
    "radiant_logo": null,
    "dire_team_name": "Yakult Brother",
    "dire_team_name_cn": "YB",
    "dire_logo": null,
    "tournament_name": null,
    "tournament_name_cn": null,
    "tournament_tier": null
  },
  {
    "id": 50,
    "match_id": 7380407733,
    "tournament_id": null,
    "radiant_team_id": "yakult-brother",
    "dire_team_id": "yakult-brother",
    "radiant_score": 45,
    "dire_score": 10,
    "radiant_game_wins": 1,
    "dire_game_wins": 0,
    "start_time": 1697237824,
    "duration": 1855,
    "series_type": "BO3",
    "status": "finished",
    "league_id": 15728,
    "game_mode": null,
    "lobby_type": 7,
    "created_at": 1770479278,
    "updated_at": 1770479278,
    "radiant_team_name": "Yakult Brother",
    "radiant_team_name_cn": "YB",
    "radiant_logo": null,
    "dire_team_name": "Yakult Brother",
    "dire_team_name_cn": "YB",
    "dire_logo": null,
    "tournament_name": null,
    "tournament_name_cn": null,
    "tournament_tier": null
  },
  {
    "id": 51,
    "match_id": 7380353553,
    "tournament_id": null,
    "radiant_team_id": "yakult-brother",
    "dire_team_id": "yakult-brother",
    "radiant_score": 47,
    "dire_score": 22,
    "radiant_game_wins": 1,
    "dire_game_wins": 0,
    "start_time": 1697233578,
    "duration": 2317,
    "series_type": "BO3",
    "status": "finished",
    "league_id": 15728,
    "game_mode": null,
    "lobby_type": 7,
    "created_at": 1770479278,
    "updated_at": 1770479278,
    "radiant_team_name": "Yakult Brother",
    "radiant_team_name_cn": "YB",
    "radiant_logo": null,
    "dire_team_name": "Yakult Brother",
    "dire_team_name_cn": "YB",
    "dire_logo": null,
    "tournament_name": null,
    "tournament_name_cn": null,
    "tournament_tier": null
  },
  {
    "id": 57,
    "match_id": 7379001957,
    "tournament_id": null,
    "radiant_team_id": "vici-gaming",
    "dire_team_id": "yakult-brother",
    "radiant_score": 22,
    "dire_score": 57,
    "radiant_game_wins": 0,
    "dire_game_wins": 1,
    "start_time": 1697167466,
    "duration": 2178,
    "series_type": "BO3",
    "status": "finished",
    "league_id": 15728,
    "game_mode": null,
    "lobby_type": 7,
    "created_at": 1770479280,
    "updated_at": 1770479280,
    "radiant_team_name": "Vici Gaming",
    "radiant_team_name_cn": "VG",
    "radiant_logo": null,
    "dire_team_name": "Yakult Brother",
    "dire_team_name_cn": "YB",
    "dire_logo": null,
    "tournament_name": null,
    "tournament_name_cn": null,
    "tournament_tier": null
  },
  {
    "id": 58,
    "match_id": 7378986342,
    "tournament_id": null,
    "radiant_team_id": "yakult-brother",
    "dire_team_id": "vici-gaming",
    "radiant_score": 33,
    "dire_score": 24,
    "radiant_game_wins": 1,
    "dire_game_wins": 0,
    "start_time": 1697165394,
    "duration": 731,
    "series_type": "BO3",
    "status": "finished",
    "league_id": 15728,
    "game_mode": null,
    "lobby_type": 7,
    "created_at": 1770479280,
    "updated_at": 1770479280,
    "radiant_team_name": "Yakult Brother",
    "radiant_team_name_cn": "YB",
    "radiant_logo": null,
    "dire_team_name": "Vici Gaming",
    "dire_team_name_cn": "VG",
    "dire_logo": null,
    "tournament_name": null,
    "tournament_name_cn": null,
    "tournament_tier": null
  },
  {
    "id": 59,
    "match_id": 7378947046,
    "tournament_id": null,
    "radiant_team_id": "yakult-brother",
    "dire_team_id": "vici-gaming",
    "radiant_score": 21,
    "dire_score": 22,
    "radiant_game_wins": 1,
    "dire_game_wins": 0,
    "start_time": 1697160972,
    "duration": 3237,
    "series_type": "BO3",
    "status": "finished",
    "league_id": 15728,
    "game_mode": null,
    "lobby_type": 7,
    "created_at": 1770479280,
    "updated_at": 1770479280,
    "radiant_team_name": "Yakult Brother",
    "radiant_team_name_cn": "YB",
    "radiant_logo": null,
    "dire_team_name": "Vici Gaming",
    "dire_team_name_cn": "VG",
    "dire_logo": null,
    "tournament_name": null,
    "tournament_name_cn": null,
    "tournament_tier": null
  },
  {
    "id": 52,
    "match_id": 7230293729,
    "tournament_id": null,
    "radiant_team_id": "yakult-brother",
    "dire_team_id": "yakult-brother",
    "radiant_score": 36,
    "dire_score": 28,
    "radiant_game_wins": 1,
    "dire_game_wins": 0,
    "start_time": 1688645407,
    "duration": 3141,
    "series_type": "BO3",
    "status": "finished",
    "league_id": 15438,
    "game_mode": null,
    "lobby_type": 7,
    "created_at": 1770479278,
    "updated_at": 1770479278,
    "radiant_team_name": "Yakult Brother",
    "radiant_team_name_cn": "YB",
    "radiant_logo": null,
    "dire_team_name": "Yakult Brother",
    "dire_team_name_cn": "YB",
    "dire_logo": null,
    "tournament_name": null,
    "tournament_name_cn": null,
    "tournament_tier": null
  },
  {
    "id": 53,
    "match_id": 7230231689,
    "tournament_id": null,
    "radiant_team_id": "yakult-brother",
    "dire_team_id": "yakult-brother",
    "radiant_score": 5,
    "dire_score": 40,
    "radiant_game_wins": 0,
    "dire_game_wins": 1,
    "start_time": 1688641932,
    "duration": 2011,
    "series_type": "BO3",
    "status": "finished",
    "league_id": 15438,
    "game_mode": null,
    "lobby_type": 7,
    "created_at": 1770479278,
    "updated_at": 1770479278,
    "radiant_team_name": "Yakult Brother",
    "radiant_team_name_cn": "YB",
    "radiant_logo": null,
    "dire_team_name": "Yakult Brother",
    "dire_team_name_cn": "YB",
    "dire_logo": null,
    "tournament_name": null,
    "tournament_name_cn": null,
    "tournament_tier": null
  },
  {
    "id": 54,
    "match_id": 7230176965,
    "tournament_id": null,
    "radiant_team_id": "yakult-brother",
    "dire_team_id": "yakult-brother",
    "radiant_score": 19,
    "dire_score": 29,
    "radiant_game_wins": 0,
    "dire_game_wins": 1,
    "start_time": 1688638202,
    "duration": 2148,
    "series_type": "BO3",
    "status": "finished",
    "league_id": 15438,
    "game_mode": null,
    "lobby_type": 7,
    "created_at": 1770479278,
    "updated_at": 1770479278,
    "radiant_team_name": "Yakult Brother",
    "radiant_team_name_cn": "YB",
    "radiant_logo": null,
    "dire_team_name": "Yakult Brother",
    "dire_team_name_cn": "YB",
    "dire_logo": null,
    "tournament_name": null,
    "tournament_name_cn": null,
    "tournament_tier": null
  },
  {
    "id": 55,
    "match_id": 7220611149,
    "tournament_id": null,
    "radiant_team_id": "yakult-brother",
    "dire_team_id": "yakult-brother",
    "radiant_score": 26,
    "dire_score": 17,
    "radiant_game_wins": 1,
    "dire_game_wins": 0,
    "start_time": 1688031746,
    "duration": 2495,
    "series_type": "BO3",
    "status": "finished",
    "league_id": 15438,
    "game_mode": null,
    "lobby_type": 7,
    "created_at": 1770479278,
    "updated_at": 1770479278,
    "radiant_team_name": "Yakult Brother",
    "radiant_team_name_cn": "YB",
    "radiant_logo": null,
    "dire_team_name": "Yakult Brother",
    "dire_team_name_cn": "YB",
    "dire_logo": null,
    "tournament_name": null,
    "tournament_name_cn": null,
    "tournament_tier": null
  },
  {
    "id": 56,
    "match_id": 7220562084,
    "tournament_id": null,
    "radiant_team_id": "yakult-brother",
    "dire_team_id": "yakult-brother",
    "radiant_score": 14,
    "dire_score": 40,
    "radiant_game_wins": 0,
    "dire_game_wins": 1,
    "start_time": 1688028187,
    "duration": 1914,
    "series_type": "BO3",
    "status": "finished",
    "league_id": 15438,
    "game_mode": null,
    "lobby_type": 7,
    "created_at": 1770479279,
    "updated_at": 1770479279,
    "radiant_team_name": "Yakult Brother",
    "radiant_team_name_cn": "YB",
    "radiant_logo": null,
    "dire_team_name": "Yakult Brother",
    "dire_team_name_cn": "YB",
    "dire_logo": null,
    "tournament_name": null,
    "tournament_name_cn": null,
    "tournament_tier": null
  },
  {
    "id": 60,
    "match_id": 5917346943,
    "tournament_id": null,
    "radiant_team_id": "vici-gaming",
    "dire_team_id": "vici-gaming",
    "radiant_score": 41,
    "dire_score": 18,
    "radiant_game_wins": 1,
    "dire_game_wins": 0,
    "start_time": 1617096369,
    "duration": 2612,
    "series_type": "BO3",
    "status": "finished",
    "league_id": 12906,
    "game_mode": null,
    "lobby_type": 7,
    "created_at": 1770479281,
    "updated_at": 1770479281,
    "radiant_team_name": "Vici Gaming",
    "radiant_team_name_cn": "VG",
    "radiant_logo": null,
    "dire_team_name": "Vici Gaming",
    "dire_team_name_cn": "VG",
    "dire_logo": null,
    "tournament_name": null,
    "tournament_name_cn": null,
    "tournament_tier": null
  },
  {
    "id": 61,
    "match_id": 5917274351,
    "tournament_id": null,
    "radiant_team_id": "vici-gaming",
    "dire_team_id": "vici-gaming",
    "radiant_score": 31,
    "dire_score": 24,
    "radiant_game_wins": 0,
    "dire_game_wins": 1,
    "start_time": 1617092705,
    "duration": 2080,
    "series_type": "BO3",
    "status": "finished",
    "league_id": 12906,
    "game_mode": null,
    "lobby_type": 7,
    "created_at": 1770479281,
    "updated_at": 1770479281,
    "radiant_team_name": "Vici Gaming",
    "radiant_team_name_cn": "VG",
    "radiant_logo": null,
    "dire_team_name": "Vici Gaming",
    "dire_team_name_cn": "VG",
    "dire_logo": null,
    "tournament_name": null,
    "tournament_name_cn": null,
    "tournament_tier": null
  }
]